pybok/__init__.py
pybok/argsconstructor.py
pybok/base.py
pybok/builder.py
pybok/configuration_properties.py
pybok/copy.py
pybok/data.py
pybok/decorators.py
pybok/equals_and_hashcode.py
pybok/getter.py
pybok/log.py
pybok/property.py
pybok/setter.py
pybok/singleton.py
pybok/to_json.py
pybok/to_string.py
pybok/types.py
pybok/utility_class.py
pybok/wither.py
pybok-0.0.1.dist-info/LICENSE
pybok-0.0.1.dist-info/WHEEL
pybok-0.0.1.dist-info/METADATA
pybok-0.0.1.dist-info/RECORD
