Metadata-Version: 2.1
Name: pybok
Version: 0.0.1
Summary: The Python library to remove all the boilerplate from your code — inspired in https://projectlombok.org/ 🔥
Home-page: https://github.com/alvgaona/pybok
License: MIT
Author: Alvaro J. Gaona
Author-email: alvgaona@gmail.com
Requires-Python: >=3.9,<4.0
Classifier: License :: OSI Approved :: MIT License
Classifier: Operating System :: OS Independent
Classifier: Programming Language :: Python :: 3
Classifier: Programming Language :: Python :: 3.9
Classifier: Programming Language :: Python :: 3.10
Classifier: Programming Language :: Python :: 3.11
Classifier: Programming Language :: Python :: 3.9
Project-URL: Repository, https://github.com/alvgaona/pybok
